araras/__init__.py
araras/email/utils.py
araras/keras/hparams.py
araras/keras/skip_connections.py
araras/keras/builders/cnn.py
araras/keras/builders/dnn.py
araras/keras/builders/lstm.py
araras/keras/builders/tcnn.py
araras/keras/callbacks/nan_loss_pruner.py
araras/keras/utils/profiler.py
araras/keras/utils/punish.py
araras/keras/utils/summary.py
araras/kernel/monitoring.py
araras/optuna/analyze.py
araras/optuna/utils.py
araras/plot/configs.py
araras/tensorflow/utils/model.py
araras/utils/cleanup.py
araras/utils/dir.py
araras/utils/gpu.py
araras/utils/logs.py
araras/utils/misc.py
araras/utils/terminal.py
araras-1.1.1.dist-info/licenses/LICENSE.txt
araras-1.1.1.dist-info/METADATA
araras-1.1.1.dist-info/WHEEL
araras-1.1.1.dist-info/top_level.txt
araras-1.1.1.dist-info/RECORD
