Metadata-Version: 2.4
Name: araras
Version: 1.1.1
Summary: A collection of tools for Machine Learning and Data Science
Author-email: Matheus Ferreira Silva <matheusferreiravga@gmail.com>
License-Expression: GPL-3.0
Classifier: Programming Language :: Python :: 3
Classifier: Operating System :: OS Independent
Requires-Python: >=3.9
License-File: LICENSE.txt
Requires-Dist: tensorflow>=2.0.0
Requires-Dist: optuna>=3.0.0
Requires-Dist: numpy>=1.20.0
Requires-Dist: matplotlib>=3.5.0
Requires-Dist: cycler>=0.11.0
Requires-Dist: scikit-learn>=1.0.0
Requires-Dist: psutil>=5.8.0
Requires-Dist: scipy>=1.7.0
Requires-Dist: fireducks>=0.9.0
Requires-Dist: ipython>=7.0.0
Requires-Dist: pretty_errors>=1.2.0
Dynamic: license-file
